pycobra/__init__.py
pycobra/classifiercobra.py
pycobra/cobra.py
pycobra/diagnostics.py
pycobra/ewa.py
pycobra/kernelcobra.py
pycobra/visualisation.py
pycobra-0.2.4.dist-info/.DS_Store
pycobra-0.2.4.dist-info/LICENSE.txt
pycobra-0.2.4.dist-info/METADATA
pycobra-0.2.4.dist-info/WHEEL
pycobra-0.2.4.dist-info/top_level.txt
pycobra-0.2.4.dist-info/RECORD
