Metadata-Version: 2.1
Name: pycobra
Version: 0.2.4
Summary: Python implementation of COBRA algorithm with regression analysis
Home-page: https://github.com/bhargavvader/pycobra
Author: Bhargav Srinivasa Desikan
Author-email: bhargavvader@gmail.com
License: MIT
Keywords: Aggregation of Predictors,Regression Analysis,Voronoi Tesselation,Statistical Aggregation
Platform: UNKNOWN
Classifier: Development Status :: 4 - Beta
Classifier: License :: OSI Approved :: MIT License
Classifier: Programming Language :: Python
Classifier: Operating System :: OS Independent
Classifier: Intended Audience :: Science/Research
Classifier: Topic :: Scientific/Engineering
Requires-Dist: numpy
Requires-Dist: scipy
Requires-Dist: scikit-learn
Requires-Dist: matplotlib
Requires-Dist: seaborn
Requires-Dist: pandas
